GalleryMan/__init__.py
GalleryMan/main.py
GalleryMan/assets/QEditorButtons.py
GalleryMan/assets/QtHelpers.py
GalleryMan/assets/QtImageProcessor.py
GalleryMan/assets/__init__.py
GalleryMan/assets/cropper.py
GalleryMan/assets/editorButtonsHelper.py
GalleryMan/assets/singleFolder.py
GalleryMan/themes/__init__.py
GalleryMan/themes/filters.py
GalleryMan/utils/__init__.py
GalleryMan/utils/doodleImage.py
GalleryMan/utils/helpers.py
GalleryMan/utils/imageDoodler.py
GalleryMan/utils/infoFinder.py
GalleryMan/utils/initer.py
GalleryMan/utils/readers.py
GalleryMan/utils/stickerManager.py
GalleryMan/utils/stickersArena.py
GalleryMan/views/__init__.py
GalleryMan/views/firstPage.py
GalleryMan/views/folderview.py
galleryman-1.0.0.dist-info/LICENSE
galleryman-1.0.0.dist-info/METADATA
galleryman-1.0.0.dist-info/WHEEL
galleryman-1.0.0.dist-info/entry_points.txt
galleryman-1.0.0.dist-info/top_level.txt
galleryman-1.0.0.dist-info/RECORD
